redcap_downloader/__init__.py
redcap_downloader/generate_config.py
redcap_downloader/main.py
redcap_downloader/config/__init__.py
redcap_downloader/config/properties.py
redcap_downloader/data_cleaning/__init__.py
redcap_downloader/data_cleaning/data_cleaner.py
redcap_downloader/data_cleaning/helpers.py
redcap_downloader/data_cleaning/replacements.py
redcap_downloader/redcap_api/__init__.py
redcap_downloader/redcap_api/dom.py
redcap_downloader/redcap_api/redcap.py
redcap_downloader/storage/__init__.py
redcap_downloader/storage/path_resolver.py
redcap_downloader-0.3.2.dist-info/licenses/LICENSE
redcap_downloader-0.3.2.dist-info/METADATA
redcap_downloader-0.3.2.dist-info/WHEEL
redcap_downloader-0.3.2.dist-info/entry_points.txt
redcap_downloader-0.3.2.dist-info/top_level.txt
redcap_downloader-0.3.2.dist-info/RECORD
