Metadata-Version: 2.4
Name: redcap_downloader
Version: 0.3.2
Summary: Download, clean-up and organise data from REDCap
Home-page: https://github.com/chronopsychiatry/REDCap_downloader
Requires-Python: >=3.10
License-File: LICENSE
Requires-Dist: pandas>=2.3.0
Requires-Dist: tabulate>=0.9.0
Requires-Dist: requests>=2.32.0
Requires-Dist: setuptools>=65.5.0
Dynamic: description-content-type
Dynamic: home-page
Dynamic: license-file
Dynamic: requires-dist
Dynamic: requires-python
Dynamic: summary
